{
    "executionTime": 0,
    "listArticle": [
        {
            "id": "LEGIARTI000042567464",
            "idTexte": null,
            "type": "AUTONOME",
            "texte": "Le cong\u00e9 de longue maladie est attribu\u00e9, apr\u00e8s \u00e9puisement des droits de cong\u00e9 de maladie ou des droits du cong\u00e9 du bless\u00e9 fix\u00e9s aux articles L. 4138-3 et L. 4138-3-1 , dans les cas autres que ceux pr\u00e9vus \u00e0 l'article L. 4138-12 , lorsque l'affection constat\u00e9e met l'int\u00e9ress\u00e9 dans l'impossibilit\u00e9 d'exercer ses fonctions et qu'elle pr\u00e9sente un caract\u00e8re invalidant et de gravit\u00e9 confirm\u00e9e. Lorsque l'affection survient du fait ou \u00e0 l'occasion de l'exercice des fonctions ou \u00e0 la suite de l'une des causes exceptionnelles pr\u00e9vues \u00e0 l'article L. 27 du code des pensions civiles et militaires de retraite, ce cong\u00e9 est d'une dur\u00e9e maximale de trois ans. Le militaire conserve, dans les conditions d\u00e9finies par d\u00e9cret en Conseil d'Etat, sa r\u00e9mun\u00e9ration. Dans les autres cas, le militaire de carri\u00e8re, ou le militaire servant en vertu d'un contrat r\u00e9unissant au moins trois ans de services militaires, b\u00e9n\u00e9ficie de ce cong\u00e9 pendant une dur\u00e9e maximale de trois ans. L'int\u00e9ress\u00e9 per\u00e7oit, dans les conditions fix\u00e9es par d\u00e9cret en Conseil d'Etat, sa r\u00e9mun\u00e9ration pendant un an, puis une r\u00e9mun\u00e9ration r\u00e9duite de moiti\u00e9 les deux ann\u00e9es qui suivent. Le militaire servant en vertu d'un contrat r\u00e9unissant moins de trois ans de services militaires b\u00e9n\u00e9ficie de ce cong\u00e9, non r\u00e9mun\u00e9r\u00e9, pendant une dur\u00e9e maximale d'un an. Le militaire qui a obtenu un cong\u00e9 de longue maladie ne peut b\u00e9n\u00e9ficier d'un cong\u00e9 de m\u00eame nature, s'il n'a pas auparavant repris l'exercice de ses fonctions pendant un an. Le militaire plac\u00e9 en cong\u00e9 de longue maladie continue \u00e0 figurer sur la liste d'anciennet\u00e9, concourt pour l'avancement \u00e0 l'anciennet\u00e9 et, dans les cas vis\u00e9s au deuxi\u00e8me alin\u00e9a du pr\u00e9sent article, pour l'avancement au choix. Le temps pass\u00e9 en cong\u00e9 est pris en compte pour l'avancement et pour les droits \u00e0 pension de retraite. Un d\u00e9cret en Conseil d'Etat fixe les conditions dans lesquelles le militaire plac\u00e9 en cong\u00e9 de longue maladie peut pratiquer des activit\u00e9s de r\u00e9adaptation, de r\u00e9insertion sociale et professionnelle et b\u00e9n\u00e9ficier, dans la position qui est la sienne, des dispositifs de reconversion pr\u00e9vus aux articles L. 4139-5 et L. 4139-5-1 du pr\u00e9sent code.",
            "texteHtml": "<p>Le cong\u00e9 de longue maladie est attribu\u00e9, apr\u00e8s \u00e9puisement des droits de cong\u00e9 de maladie ou des droits du cong\u00e9 du bless\u00e9 fix\u00e9s aux articles <a href='/affichCodeArticle.do?cidTexte=LEGITEXT000006071307&idArticle=LEGIARTI000006540307&dateTexte=&categorieLien=cid'>L. 4138-3 </a>et <a href='/affichCodeArticle.do?cidTexte=LEGITEXT000006071307&idArticle=LEGIARTI000029221870&dateTexte=&categorieLien=cid' title='Code de la d\u00e9fense. - art. L4138-3-1 (V)'>L. 4138-3-1</a>, dans les cas autres que ceux pr\u00e9vus \u00e0 l'article <a href='/affichCodeArticle.do?cidTexte=LEGITEXT000006071307&idArticle=LEGIARTI000042567475&dateTexte=&categorieLien=id' title='Code de la d\u00e9fense. - art. L4138-12 (V)'>L. 4138-12</a>, lorsque l'affection constat\u00e9e met l'int\u00e9ress\u00e9 dans l'impossibilit\u00e9 d'exercer ses fonctions et qu'elle pr\u00e9sente un caract\u00e8re invalidant et de gravit\u00e9 confirm\u00e9e. </p><p>Lorsque l'affection survient du fait ou \u00e0 l'occasion de l'exercice des fonctions ou \u00e0 la suite de l'une des causes exceptionnelles pr\u00e9vues \u00e0 l'article <a href='/affichCodeArticle.do?cidTexte=LEGITEXT000006070302&idArticle=LEGIARTI000006362741&dateTexte=&categorieLien=cid'>L. 27 </a>du code des pensions civiles et militaires de retraite, ce cong\u00e9 est d'une dur\u00e9e maximale de trois ans. Le militaire conserve, dans les conditions d\u00e9finies par d\u00e9cret en Conseil d'Etat, sa r\u00e9mun\u00e9ration. </p><p>Dans les autres cas, le militaire de carri\u00e8re, ou le militaire servant en vertu d'un contrat r\u00e9unissant au moins trois ans de services militaires, b\u00e9n\u00e9ficie de ce cong\u00e9 pendant une dur\u00e9e maximale de trois ans. L'int\u00e9ress\u00e9 per\u00e7oit, dans les conditions fix\u00e9es par d\u00e9cret en Conseil d'Etat, sa r\u00e9mun\u00e9ration pendant un an, puis une r\u00e9mun\u00e9ration r\u00e9duite de moiti\u00e9 les deux ann\u00e9es qui suivent. Le militaire servant en vertu d'un contrat r\u00e9unissant moins de trois ans de services militaires b\u00e9n\u00e9ficie de ce cong\u00e9, non r\u00e9mun\u00e9r\u00e9, pendant une dur\u00e9e maximale d'un an. </p><p>Le militaire qui a obtenu un cong\u00e9 de longue maladie ne peut b\u00e9n\u00e9ficier d'un cong\u00e9 de m\u00eame nature, s'il n'a pas auparavant repris l'exercice de ses fonctions pendant un an. </p><p>Le militaire plac\u00e9 en cong\u00e9 de longue maladie continue \u00e0 figurer sur la liste d'anciennet\u00e9, concourt pour l'avancement \u00e0 l'anciennet\u00e9 et, dans les cas vis\u00e9s au deuxi\u00e8me alin\u00e9a du pr\u00e9sent article, pour l'avancement au choix. Le temps pass\u00e9 en cong\u00e9 est pris en compte pour l'avancement et pour les droits \u00e0 pension de retraite. </p><p>Un d\u00e9cret en Conseil d'Etat fixe les conditions dans lesquelles le militaire plac\u00e9 en cong\u00e9 de longue maladie peut pratiquer des activit\u00e9s de r\u00e9adaptation, de r\u00e9insertion sociale et professionnelle et b\u00e9n\u00e9ficier, dans la position qui est la sienne, des dispositifs de reconversion pr\u00e9vus aux articles <a href='/affichCodeArticle.do?cidTexte=LEGITEXT000006071307&idArticle=LEGIARTI000006540329&dateTexte=&categorieLien=cid' title='Code de la d\u00e9fense. - art. L4139-5 (V)'>L. 4139-5 </a>et <a href='/affichCodeArticle.do?cidTexte=LEGITEXT000006071307&idArticle=LEGIARTI000023377117&dateTexte=&categorieLien=cid' title='Code de la d\u00e9fense. - art. L4139-5-1 (V)'>L. 4139-5-1</a> du pr\u00e9sent code.</p>",
            "num": "L4138-13",
            "origine": "LEGI",
            "nature": "Article",
            "versionArticle": "5.0",
            "etat": "VIGUEUR",
            "dateDebut": 1606435200000,
            "dateFin": 32472144000000,
            "dateDebutExtension": 32472144000000,
            "dateFinExtension": 32472144000000,
            "inap": null,
            "ordre": 128847,
            "context": {
                "titresTM": [
                    {
                        "debut": "2004-12-21",
                        "fin": "2999-01-01",
                        "titre": "Partie l\u00e9gislative",
                        "xPath": "/ARTICLE/CONTEXTE/TEXTE/TM/TITRE_TM",
                        "cid": "LEGISCTA000006096399",
                        "id": "LEGISCTA000006096399",
                        "etat": "VIGUEUR"
                    },
                    {
                        "debut": "2007-03-30",
                        "fin": "2999-01-01",
                        "titre": "PARTIE 4 : LE PERSONNEL MILITAIRE",
                        "xPath": "/ARTICLE/CONTEXTE/TEXTE/TM/TM/TITRE_TM",
                        "cid": "LEGISCTA000006120662",
                        "id": "LEGISCTA000006120662",
                        "etat": "VIGUEUR"
                    },
                    {
                        "debut": "2007-03-30",
                        "fin": "2999-01-01",
                        "titre": "LIVRE Ier : STATUT G\u00c9N\u00c9RAL DES MILITAIRES",
                        "xPath": "/ARTICLE/CONTEXTE/TEXTE/TM/TM/TM/TITRE_TM",
                        "cid": "LEGISCTA000006137720",
                        "id": "LEGISCTA000006137720",
                        "etat": "VIGUEUR"
                    },
                    {
                        "debut": "2007-03-30",
                        "fin": "2999-01-01",
                        "titre": "TITRE III : DISPOSITIONS STATUTAIRES RELATIVES AUX D\u00c9ROULEMENTS DES CARRI\u00c8RES",
                        "xPath": "/ARTICLE/CONTEXTE/TEXTE/TM/TM/TM/TM/TITRE_TM",
                        "cid": "LEGISCTA000006151518",
                        "id": "LEGISCTA000006151518",
                        "etat": "VIGUEUR"
                    },
                    {
                        "debut": "2007-03-30",
                        "fin": "2999-01-01",
                        "titre": "Chapitre VIII : Positions statutaires",
                        "xPath": "/ARTICLE/CONTEXTE/TEXTE/TM/TM/TM/TM/TM/TITRE_TM",
                        "cid": "LEGISCTA000006166980",
                        "id": "LEGISCTA000006166980",
                        "etat": "VIGUEUR"
                    },
                    {
                        "debut": "2007-03-30",
                        "fin": "2999-01-01",
                        "titre": "Section 4 : Non-activit\u00e9",
                        "xPath": "/ARTICLE/CONTEXTE/TEXTE/TM/TM/TM/TM/TM/TM/TITRE_TM",
                        "cid": "LEGISCTA000006182633",
                        "id": "LEGISCTA000006182633",
                        "etat": "VIGUEUR"
                    }
                ],
                "nombreVersionParent": 1,
                "longeurChemin": 50,
                "titreTxt": [
                    {
                        "debut": "2004-12-21",
                        "fin": "2999-01-01",
                        "titre": "Code de la d\u00e9fense",
                        "xPath": "/ARTICLE/CONTEXTE/TEXTE/TITRE_TXT",
                        "cid": "LEGITEXT000006071307",
                        "id": "LEGITEXT000006071307",
                        "etat": "VIGUEUR"
                    }
                ]
            },
            "cid": "LEGIARTI000006540318",
            "cidTexte": null,
            "sectionParentCid": "LEGISCTA000006182633",
            "sectionParentId": "LEGISCTA000006182633",
            "sectionParentTitre": "Section 4 : Non-activit\u00e9",
            "fullSectionsTitre": "Partie l\u00e9gislative &gt; PARTIE 4 : LE PERSONNEL MILITAIRE &gt; LIVRE Ier : STATUT G\u00c9N\u00c9RAL DES MILITAIRES &gt; TITRE III : DISPOSITIONS STATUTAIRES RELATIVES AUX D\u00c9ROULEMENTS DES CARRI\u00c8RES &gt; Chapitre VIII : Positions statutaires &gt; Section 4 : Non-activit\u00e9",
            "refInjection": "IG-20230926",
            "idTechInjection": "LEGIARTI000042567464",
            "idEli": null,
            "idEliAlias": null,
            "calipsos": [],
            "textTitles": [
                {
                    "id": "LEGITEXT000006071307",
                    "titre": "Code de la d\u00e9fense.",
                    "titreLong": "Code de la d\u00e9fense",
                    "etat": "VIGUEUR",
                    "dateDebut": 1103587200000,
                    "dateFin": 32472144000000,
                    "cid": "LEGITEXT000006071307",
                    "datePubli": 32472144000000,
                    "datePubliComputed": null,
                    "dateTexte": 32472144000000,
                    "dateTexteComputed": null,
                    "nature": "CODE",
                    "nor": "",
                    "num": "",
                    "numParution": "",
                    "originePubli": "",
                    "appliGeo": null,
                    "codesNomenclatures": [],
                    "visas": null,
                    "nota": null,
                    "notice": null,
                    "travauxPreparatoires": null,
                    "signataires": null,
                    "dossiersLegislatifs": [],
                    "ancienId": null,
                    "appellations": null
                }
            ],
            "nota": "",
            "notaHtml": "",
            "activitePro": [],
            "numeroBrochure": [],
            "numeroBo": null,
            "conteneurs": [],
            "lienModifications": [
                {
                    "textCid": "JORFTEXT000000466960",
                    "textTitle": "Ordonnance n\u00b0 2007-465 du 29 mars 2007 - art. Annexe (V)",
                    "linkType": "CODIFICATION",
                    "linkOrientation": "source",
                    "articleNum": "",
                    "articleId": "",
                    "natureText": "",
                    "datePubliTexte": null,
                    "dateSignaTexte": null,
                    "dateDebutCible": null
                },
                {
                    "textCid": "JORFTEXT000042565176",
                    "textTitle": "Ordonnance n\u00b02020-1447 du 25 novembre 2020 - art. 6",
                    "linkType": "MODIFIE",
                    "linkOrientation": "cible",
                    "articleNum": "6",
                    "articleId": "LEGIARTI000042565864",
                    "natureText": "ORDONNANCE",
                    "datePubliTexte": "2020-11-26",
                    "dateSignaTexte": "2020-11-25",
                    "dateDebutCible": "2020-11-27"
                }
            ],
            "lienCitations": [
                {
                    "textCid": "JORFTEXT000042238259",
                    "textTitle": "D\u00e9cret n\u00b02020-1057 du 14 ao\u00fbt 2020 - art. 4 (V)",
                    "linkType": "CITATION",
                    "linkOrientation": "cible",
                    "articleNum": "4",
                    "articleId": "LEGIARTI000042239454",
                    "natureText": "DECRET",
                    "parentCid": null,
                    "numTexte": "2020-1057",
                    "datePubli": 1597449600000,
                    "dateDebut": 1597536000000
                },
                {
                    "textCid": "JORFTEXT000044591334",
                    "textTitle": "Arr\u00eat\u00e9 du 21 d\u00e9cembre 2021 - art. 2, v. init.",
                    "linkType": "CITATION",
                    "linkOrientation": "cible",
                    "articleNum": "2",
                    "articleId": "JORFARTI000044591338",
                    "natureText": "ARRETE",
                    "parentCid": null,
                    "numTexte": "",
                    "datePubli": 1640736000000,
                    "dateDebut": 32472144000000
                },
                {
                    "textCid": "LEGITEXT000006070302",
                    "textTitle": "Code des pensions civiles et militaires de retraite - art. L27",
                    "linkType": "CITATION",
                    "linkOrientation": "source",
                    "articleNum": "L27",
                    "articleId": "LEGIARTI000006362741",
                    "natureText": "CODE",
                    "parentCid": null,
                    "numTexte": "",
                    "datePubli": 32472144000000,
                    "dateDebut": 1565222400000
                },
                {
                    "textCid": "LEGITEXT000006071307",
                    "textTitle": "Code de la d\u00e9fense. - art. L4138-12 (V)",
                    "linkType": "CITATION",
                    "linkOrientation": "source",
                    "articleNum": "L4138-12",
                    "articleId": "LEGIARTI000042567475",
                    "natureText": "CODE",
                    "parentCid": null,
                    "numTexte": "",
                    "datePubli": 32472144000000,
                    "dateDebut": 1606435200000
                },
                {
                    "textCid": "LEGITEXT000006071307",
                    "textTitle": "Code de la d\u00e9fense. - art. L4138-3",
                    "linkType": "CITATION",
                    "linkOrientation": "source",
                    "articleNum": "L4138-3",
                    "articleId": "LEGIARTI000006540307",
                    "natureText": "CODE",
                    "parentCid": null,
                    "numTexte": "",
                    "datePubli": 32472144000000,
                    "dateDebut": 1175212800000
                },
                {
                    "textCid": "LEGITEXT000006071307",
                    "textTitle": "Code de la d\u00e9fense. - art. L4138-3-1 (V)",
                    "linkType": "CITATION",
                    "linkOrientation": "source",
                    "articleNum": "L4138-3-1",
                    "articleId": "LEGIARTI000029221870",
                    "natureText": "CODE",
                    "parentCid": null,
                    "numTexte": "",
                    "datePubli": 32472144000000,
                    "dateDebut": 1606435200000
                },
                {
                    "textCid": "LEGITEXT000006071307",
                    "textTitle": "Code de la d\u00e9fense. - art. L4139-5 (V)",
                    "linkType": "CITATION",
                    "linkOrientation": "source",
                    "articleNum": "L4139-5",
                    "articleId": "LEGIARTI000006540329",
                    "natureText": "CODE",
                    "parentCid": null,
                    "numTexte": "",
                    "datePubli": 32472144000000,
                    "dateDebut": 1531612800000
                },
                {
                    "textCid": "LEGITEXT000006071307",
                    "textTitle": "Code de la d\u00e9fense. - art. L4139-5-1 (V)",
                    "linkType": "CITATION",
                    "linkOrientation": "source",
                    "articleNum": "L4139-5-1",
                    "articleId": "LEGIARTI000023377117",
                    "natureText": "CODE",
                    "parentCid": null,
                    "numTexte": "",
                    "datePubli": 32472144000000,
                    "dateDebut": 1294358400000
                },
                {
                    "textCid": "LEGITEXT000006071307",
                    "textTitle": "Code de la d\u00e9fense. - art. L4341-1 (VT)",
                    "linkType": "CITATION",
                    "linkOrientation": "cible",
                    "articleNum": "L4341-1",
                    "articleId": "LEGIARTI000037805833",
                    "natureText": "CODE",
                    "parentCid": null,
                    "numTexte": "",
                    "datePubli": 32472144000000,
                    "dateDebut": 1544745600000
                },
                {
                    "textCid": "LEGITEXT000006071307",
                    "textTitle": "Code de la d\u00e9fense. - art. R4138-58 (V)",
                    "linkType": "CITATION",
                    "linkOrientation": "cible",
                    "articleNum": "R4138-58",
                    "articleId": "LEGIARTI000033992875",
                    "natureText": "CODE",
                    "parentCid": null,
                    "numTexte": "",
                    "datePubli": 32472144000000,
                    "dateDebut": 1486339200000
                }
            ],
            "lienConcordes": [
                {
                    "textCid": "JORFTEXT000000808186",
                    "textTitle": "Loi 2005-270 2005-03-24 art. 56",
                    "linkType": "CONCORDANCE",
                    "linkOrientation": "source",
                    "articleNum": "",
                    "articleId": "JORFTEXT000000808186",
                    "natureText": "LOI"
                },
                {
                    "textCid": "JORFTEXT000000808186",
                    "textTitle": "Loi n\u00b02005-270 du 24 mars 2005 - art. 56 (Ab)",
                    "linkType": "CONCORDE",
                    "linkOrientation": "cible",
                    "articleNum": "56",
                    "articleId": "LEGIARTI000006405057",
                    "natureText": "LOI"
                }
            ],
            "lienAutres": [],
            "articleVersions": [
                {
                    "id": "LEGIARTI000006540318",
                    "etat": "MODIFIE",
                    "version": "1.0",
                    "dateDebut": 1175212800000,
                    "dateFin": 1211932800000,
                    "numero": null,
                    "ordre": null
                },
                {
                    "id": "LEGIARTI000018882454",
                    "etat": "MODIFIE",
                    "version": "2.0",
                    "dateDebut": 1211932800000,
                    "dateFin": 1405123200000,
                    "numero": null,
                    "ordre": null
                },
                {
                    "id": "LEGIARTI000029227676",
                    "etat": "MODIFIE",
                    "version": "3.0",
                    "dateDebut": 1405123200000,
                    "dateFin": 1469145600000,
                    "numero": null,
                    "ordre": null
                },
                {
                    "id": "LEGIARTI000033062981",
                    "etat": "MODIFIE",
                    "version": "4.0",
                    "dateDebut": 1469145600000,
                    "dateFin": 1606435200000,
                    "numero": null,
                    "ordre": null
                },
                {
                    "id": "LEGIARTI000042567464",
                    "etat": "VIGUEUR",
                    "version": "5.0",
                    "dateDebut": 1606435200000,
                    "dateFin": 32472144000000,
                    "numero": null,
                    "ordre": null
                }
            ],
            "computedNums": [
                "L4138-13",
                "4138-13"
            ],
            "versionPrecedente": "LEGIARTI000033062981",
            "conditionDiffere": null,
            "historique": null,
            "surtitre": null,
            "renvoi": null,
            "infosComplementaires": null,
            "infosComplementairesHtml": null,
            "infosRestructurationBranche": null,
            "infosRestructurationBrancheHtml": null
        },
        {
            "id": "LEGIARTI000033062981",
            "idTexte": null,
            "type": "AUTONOME",
            "texte": "Le cong\u00e9 de longue maladie est attribu\u00e9, apr\u00e8s \u00e9puisement des droits de cong\u00e9 de maladie ou des droits du cong\u00e9 du bless\u00e9 fix\u00e9s aux articles L. 4138-3 et L. 4138-3-1 , dans les cas autres que ceux pr\u00e9vus \u00e0 l'article L. 4138-12 , lorsque l'affection constat\u00e9e met l'int\u00e9ress\u00e9 dans l'impossibilit\u00e9 d'exercer ses fonctions et qu'elle pr\u00e9sente un caract\u00e8re invalidant et de gravit\u00e9 confirm\u00e9e. Lorsque l'affection survient du fait ou \u00e0 l'occasion de l'exercice des fonctions ou \u00e0 la suite de l'une des causes exceptionnelles pr\u00e9vues \u00e0 l'article L. 27 du code des pensions civiles et militaires de retraite, ce cong\u00e9 est d'une dur\u00e9e maximale de trois ans. Le militaire conserve, dans les conditions d\u00e9finies par d\u00e9cret en Conseil d'Etat, sa r\u00e9mun\u00e9ration. Dans les autres cas, le militaire de carri\u00e8re, ou le militaire servant en vertu d'un contrat r\u00e9unissant au moins trois ans de services militaires, b\u00e9n\u00e9ficie de ce cong\u00e9 pendant une dur\u00e9e maximale de trois ans. L'int\u00e9ress\u00e9 per\u00e7oit, dans les conditions fix\u00e9es par d\u00e9cret en Conseil d'Etat, sa r\u00e9mun\u00e9ration pendant un an, puis une r\u00e9mun\u00e9ration r\u00e9duite de moiti\u00e9 les deux ann\u00e9es qui suivent. Le militaire servant en vertu d'un contrat r\u00e9unissant moins de trois ans de services militaires b\u00e9n\u00e9ficie de ce cong\u00e9, non r\u00e9mun\u00e9r\u00e9, pendant une dur\u00e9e maximale d'un an. Le militaire qui a obtenu un cong\u00e9 de longue maladie ne peut b\u00e9n\u00e9ficier d'un cong\u00e9 de m\u00eame nature, s'il n'a pas auparavant repris l'exercice de ses fonctions pendant un an. Le militaire plac\u00e9 en cong\u00e9 de longue maladie continue \u00e0 figurer sur la liste d'anciennet\u00e9, concourt pour l'avancement \u00e0 l'anciennet\u00e9 et, dans les cas vis\u00e9s au deuxi\u00e8me alin\u00e9a du pr\u00e9sent article, pour l'avancement au choix. Le temps pass\u00e9 en cong\u00e9 est pris en compte pour l'avancement et pour les droits \u00e0 pension de retraite.",
            "texteHtml": "<p>Le cong\u00e9 de longue maladie est attribu\u00e9, apr\u00e8s \u00e9puisement des droits de cong\u00e9 de maladie ou des droits du cong\u00e9 du bless\u00e9 fix\u00e9s aux <a href='/affichCodeArticle.do?cidTexte=LEGITEXT000006071307&idArticle=LEGIARTI000006540307&dateTexte=&categorieLien=cid'>articles L. 4138-3 et L. 4138-3-1</a>, dans les cas autres que ceux pr\u00e9vus \u00e0 l'article <a href='/affichCodeArticle.do?cidTexte=LEGITEXT000006071307&idArticle=LEGIARTI000029227681&dateTexte=&categorieLien=id' title='Code de la d\u00e9fense. - art. L4138-12 (M)'>L. 4138-12</a>, lorsque l'affection constat\u00e9e met l'int\u00e9ress\u00e9 dans l'impossibilit\u00e9 d'exercer ses fonctions et qu'elle pr\u00e9sente un caract\u00e8re invalidant et de gravit\u00e9 confirm\u00e9e. </p><p>Lorsque l'affection survient du fait ou \u00e0 l'occasion de l'exercice des fonctions ou \u00e0 la suite de l'une des causes exceptionnelles pr\u00e9vues \u00e0 l'article <a href='/affichCodeArticle.do?cidTexte=LEGITEXT000006070302&idArticle=LEGIARTI000006362741&dateTexte=&categorieLien=cid'>L. 27 </a>du code des pensions civiles et militaires de retraite, ce cong\u00e9 est d'une dur\u00e9e maximale de trois ans. Le militaire conserve, dans les conditions d\u00e9finies par d\u00e9cret en Conseil d'Etat, sa r\u00e9mun\u00e9ration. </p><p>Dans les autres cas, le militaire de carri\u00e8re, ou le militaire servant en vertu d'un contrat r\u00e9unissant au moins trois ans de services militaires, b\u00e9n\u00e9ficie de ce cong\u00e9 pendant une dur\u00e9e maximale de trois ans. L'int\u00e9ress\u00e9 per\u00e7oit, dans les conditions fix\u00e9es par d\u00e9cret en Conseil d'Etat, sa r\u00e9mun\u00e9ration pendant un an, puis une r\u00e9mun\u00e9ration r\u00e9duite de moiti\u00e9 les deux ann\u00e9es qui suivent. Le militaire servant en vertu d'un contrat r\u00e9unissant moins de trois ans de services militaires b\u00e9n\u00e9ficie de ce cong\u00e9, non r\u00e9mun\u00e9r\u00e9, pendant une dur\u00e9e maximale d'un an. </p><p>Le militaire qui a obtenu un cong\u00e9 de longue maladie ne peut b\u00e9n\u00e9ficier d'un cong\u00e9 de m\u00eame nature, s'il n'a pas auparavant repris l'exercice de ses fonctions pendant un an. </p><p>Le militaire plac\u00e9 en cong\u00e9 de longue maladie continue \u00e0 figurer sur la liste d'anciennet\u00e9, concourt pour l'avancement \u00e0 l'anciennet\u00e9 et, dans les cas vis\u00e9s au deuxi\u00e8me alin\u00e9a du pr\u00e9sent article, pour l'avancement au choix. Le temps pass\u00e9 en cong\u00e9 est pris en compte pour l'avancement et pour les droits \u00e0 pension de retraite.</p>",
            "num": "L4138-13",
            "origine": "LEGI",
            "nature": "Article",
            "versionArticle": "4.0",
            "etat": "MODIFIE",
            "dateDebut": 1469145600000,
            "dateFin": 1606435200000,
            "dateDebutExtension": 32472144000000,
            "dateFinExtension": 32472144000000,
            "inap": null,
            "ordre": 128847,
            "context": {
                "titresTM": [
                    {
                        "debut": "2004-12-21",
                        "fin": "2999-01-01",
                        "titre": "Partie l\u00e9gislative",
                        "xPath": "/ARTICLE/CONTEXTE/TEXTE/TM/TITRE_TM",
                        "cid": "LEGISCTA000006096399",
                        "id": "LEGISCTA000006096399",
                        "etat": "VIGUEUR"
                    },
                    {
                        "debut": "2007-03-30",
                        "fin": "2999-01-01",
                        "titre": "PARTIE 4 : LE PERSONNEL MILITAIRE",
                        "xPath": "/ARTICLE/CONTEXTE/TEXTE/TM/TM/TITRE_TM",
                        "cid": "LEGISCTA000006120662",
                        "id": "LEGISCTA000006120662",
                        "etat": "VIGUEUR"
                    },
                    {
                        "debut": "2007-03-30",
                        "fin": "2999-01-01",
                        "titre": "LIVRE Ier : STATUT G\u00c9N\u00c9RAL DES MILITAIRES",
                        "xPath": "/ARTICLE/CONTEXTE/TEXTE/TM/TM/TM/TITRE_TM",
                        "cid": "LEGISCTA000006137720",
                        "id": "LEGISCTA000006137720",
                        "etat": "VIGUEUR"
                    },
                    {
                        "debut": "2007-03-30",
                        "fin": "2999-01-01",
                        "titre": "TITRE III : DISPOSITIONS STATUTAIRES RELATIVES AUX D\u00c9ROULEMENTS DES CARRI\u00c8RES",
                        "xPath": "/ARTICLE/CONTEXTE/TEXTE/TM/TM/TM/TM/TITRE_TM",
                        "cid": "LEGISCTA000006151518",
                        "id": "LEGISCTA000006151518",
                        "etat": "VIGUEUR"
                    },
                    {
                        "debut": "2007-03-30",
                        "fin": "2999-01-01",
                        "titre": "Chapitre VIII : Positions statutaires",
                        "xPath": "/ARTICLE/CONTEXTE/TEXTE/TM/TM/TM/TM/TM/TITRE_TM",
                        "cid": "LEGISCTA000006166980",
                        "id": "LEGISCTA000006166980",
                        "etat": "VIGUEUR"
                    },
                    {
                        "debut": "2007-03-30",
                        "fin": "2999-01-01",
                        "titre": "Section 4 : Non-activit\u00e9",
                        "xPath": "/ARTICLE/CONTEXTE/TEXTE/TM/TM/TM/TM/TM/TM/TITRE_TM",
                        "cid": "LEGISCTA000006182633",
                        "id": "LEGISCTA000006182633",
                        "etat": "VIGUEUR"
                    }
                ],
                "nombreVersionParent": 1,
                "longeurChemin": 50,
                "titreTxt": [
                    {
                        "debut": "2004-12-21",
                        "fin": "2999-01-01",
                        "titre": "Code de la d\u00e9fense",
                        "xPath": "/ARTICLE/CONTEXTE/TEXTE/TITRE_TXT",
                        "cid": "LEGITEXT000006071307",
                        "id": "LEGITEXT000006071307",
                        "etat": "VIGUEUR"
                    }
                ]
            },
            "cid": "LEGIARTI000006540318",
            "cidTexte": null,
            "sectionParentCid": "LEGISCTA000006182633",
            "sectionParentId": "LEGISCTA000006182633",
            "sectionParentTitre": "Section 4 : Non-activit\u00e9",
            "fullSectionsTitre": "Partie l\u00e9gislative &gt; PARTIE 4 : LE PERSONNEL MILITAIRE &gt; LIVRE Ier : STATUT G\u00c9N\u00c9RAL DES MILITAIRES &gt; TITRE III : DISPOSITIONS STATUTAIRES RELATIVES AUX D\u00c9ROULEMENTS DES CARRI\u00c8RES &gt; Chapitre VIII : Positions statutaires &gt; Section 4 : Non-activit\u00e9",
            "refInjection": "IG-20230926",
            "idTechInjection": "LEGIARTI000033062981",
            "idEli": null,
            "idEliAlias": null,
            "calipsos": [],
            "textTitles": [
                {
                    "id": "LEGITEXT000006071307",
                    "titre": "Code de la d\u00e9fense.",
                    "titreLong": "Code de la d\u00e9fense",
                    "etat": "VIGUEUR",
                    "dateDebut": 1103587200000,
                    "dateFin": 32472144000000,
                    "cid": "LEGITEXT000006071307",
                    "datePubli": 32472144000000,
                    "datePubliComputed": null,
                    "dateTexte": 32472144000000,
                    "dateTexteComputed": null,
                    "nature": "CODE",
                    "nor": "",
                    "num": "",
                    "numParution": "",
                    "originePubli": "",
                    "appliGeo": null,
                    "codesNomenclatures": [],
                    "visas": null,
                    "nota": null,
                    "notice": null,
                    "travauxPreparatoires": null,
                    "signataires": null,
                    "dossiersLegislatifs": [],
                    "ancienId": null,
                    "appellations": null
                }
            ],
            "nota": "",
            "notaHtml": "",
            "activitePro": [],
            "numeroBrochure": [],
            "numeroBo": null,
            "conteneurs": [],
            "lienModifications": [
                {
                    "textCid": "JORFTEXT000000466960",
                    "textTitle": "Ordonnance n\u00b0 2007-465 du 29 mars 2007 - art. Annexe (V)",
                    "linkType": "CODIFICATION",
                    "linkOrientation": "source",
                    "articleNum": "Annexe",
                    "articleId": "LEGIARTI000036687012",
                    "natureText": "ORDONNANCE",
                    "datePubliTexte": "2007-03-30",
                    "dateSignaTexte": "2007-03-29",
                    "dateDebutCible": "2007-03-30"
                },
                {
                    "textCid": "JORFTEXT000032918268",
                    "textTitle": "Ordonnance n\u00b0 2016-982 du 20 juillet 2016 - art. 5",
                    "linkType": "MODIFIE",
                    "linkOrientation": "cible",
                    "articleNum": "5",
                    "articleId": "LEGIARTI000032918766",
                    "natureText": "ORDONNANCE",
                    "datePubliTexte": "2016-07-21",
                    "dateSignaTexte": "2016-07-20",
                    "dateDebutCible": "2016-07-22"
                }
            ],
            "lienCitations": [
                {
                    "textCid": "JORFTEXT000042238259",
                    "textTitle": "D\u00e9cret n\u00b02020-1057 du 14 ao\u00fbt 2020 - art. 4 (V)",
                    "linkType": "CITATION",
                    "linkOrientation": "cible",
                    "articleNum": "4",
                    "articleId": "LEGIARTI000042239454",
                    "natureText": "DECRET",
                    "parentCid": null,
                    "numTexte": "2020-1057",
                    "datePubli": 1597449600000,
                    "dateDebut": 1597536000000
                },
                {
                    "textCid": "JORFTEXT000044591334",
                    "textTitle": "Arr\u00eat\u00e9 du 21 d\u00e9cembre 2021 - art. 2, v. init.",
                    "linkType": "CITATION",
                    "linkOrientation": "cible",
                    "articleNum": "2",
                    "articleId": "JORFARTI000044591338",
                    "natureText": "ARRETE",
                    "parentCid": null,
                    "numTexte": "",
                    "datePubli": 1640736000000,
                    "dateDebut": 32472144000000
                },
                {
                    "textCid": "LEGITEXT000006070302",
                    "textTitle": "Code des pensions civiles et militaires de retraite - art. L27",
                    "linkType": "CITATION",
                    "linkOrientation": "source",
                    "articleNum": "L27",
                    "articleId": "LEGIARTI000006362741",
                    "natureText": "CODE",
                    "parentCid": null,
                    "numTexte": "",
                    "datePubli": 32472144000000,
                    "dateDebut": 1565222400000
                },
                {
                    "textCid": "LEGITEXT000006071307",
                    "textTitle": "Code de la d\u00e9fense. - art. L4138-12 (M)",
                    "linkType": "CITATION",
                    "linkOrientation": "source",
                    "articleNum": "L4138-12",
                    "articleId": "LEGIARTI000029227681",
                    "natureText": "CODE",
                    "parentCid": null,
                    "numTexte": "",
                    "datePubli": 32472144000000,
                    "dateDebut": 1405123200000
                },
                {
                    "textCid": "LEGITEXT000006071307",
                    "textTitle": "Code de la d\u00e9fense. - art. L4138-3",
                    "linkType": "CITATION",
                    "linkOrientation": "source",
                    "articleNum": "L4138-3",
                    "articleId": "LEGIARTI000006540307",
                    "natureText": "CODE",
                    "parentCid": null,
                    "numTexte": "",
                    "datePubli": 32472144000000,
                    "dateDebut": 1175212800000
                },
                {
                    "textCid": "LEGITEXT000006071307",
                    "textTitle": "Code de la d\u00e9fense. - art. L4341-1 (VT)",
                    "linkType": "CITATION",
                    "linkOrientation": "cible",
                    "articleNum": "L4341-1",
                    "articleId": "LEGIARTI000037805833",
                    "natureText": "CODE",
                    "parentCid": null,
                    "numTexte": "",
                    "datePubli": 32472144000000,
                    "dateDebut": 1544745600000
                },
                {
                    "textCid": "LEGITEXT000006071307",
                    "textTitle": "Code de la d\u00e9fense. - art. R4138-58 (V)",
                    "linkType": "CITATION",
                    "linkOrientation": "cible",
                    "articleNum": "R4138-58",
                    "articleId": "LEGIARTI000033992875",
                    "natureText": "CODE",
                    "parentCid": null,
                    "numTexte": "",
                    "datePubli": 32472144000000,
                    "dateDebut": 1486339200000
                }
            ],
            "lienConcordes": [
                {
                    "textCid": "JORFTEXT000000808186",
                    "textTitle": "Loi 2005-270 2005-03-24 art. 56",
                    "linkType": "CONCORDANCE",
                    "linkOrientation": "source",
                    "articleNum": "",
                    "articleId": "JORFTEXT000000808186",
                    "natureText": "LOI"
                },
                {
                    "textCid": "JORFTEXT000000808186",
                    "textTitle": "Loi n\u00b02005-270 du 24 mars 2005 - art. 56 (Ab)",
                    "linkType": "CONCORDE",
                    "linkOrientation": "cible",
                    "articleNum": "56",
                    "articleId": "LEGIARTI000006405057",
                    "natureText": "LOI"
                }
            ],
            "lienAutres": [],
            "articleVersions": [
                {
                    "id": "LEGIARTI000006540318",
                    "etat": "MODIFIE",
                    "version": "1.0",
                    "dateDebut": 1175212800000,
                    "dateFin": 1211932800000,
                    "numero": null,
                    "ordre": null
                },
                {
                    "id": "LEGIARTI000018882454",
                    "etat": "MODIFIE",
                    "version": "2.0",
                    "dateDebut": 1211932800000,
                    "dateFin": 1405123200000,
                    "numero": null,
                    "ordre": null
                },
                {
                    "id": "LEGIARTI000029227676",
                    "etat": "MODIFIE",
                    "version": "3.0",
                    "dateDebut": 1405123200000,
                    "dateFin": 1469145600000,
                    "numero": null,
                    "ordre": null
                },
                {
                    "id": "LEGIARTI000033062981",
                    "etat": "MODIFIE",
                    "version": "4.0",
                    "dateDebut": 1469145600000,
                    "dateFin": 1606435200000,
                    "numero": null,
                    "ordre": null
                },
                {
                    "id": "LEGIARTI000042567464",
                    "etat": "VIGUEUR",
                    "version": "5.0",
                    "dateDebut": 1606435200000,
                    "dateFin": 32472144000000,
                    "numero": null,
                    "ordre": null
                }
            ],
            "computedNums": [
                "L4138-13",
                "4138-13"
            ],
            "versionPrecedente": "LEGIARTI000029227676",
            "conditionDiffere": null,
            "historique": null,
            "surtitre": null,
            "renvoi": null,
            "infosComplementaires": null,
            "infosComplementairesHtml": null,
            "infosRestructurationBranche": null,
            "infosRestructurationBrancheHtml": null
        },
        {
            "id": "LEGIARTI000029227676",
            "idTexte": null,
            "type": "AUTONOME",
            "texte": "Le cong\u00e9 de longue maladie est attribu\u00e9, apr\u00e8s \u00e9puisement des droits de cong\u00e9 de maladie ou des droits du cong\u00e9 du bless\u00e9 fix\u00e9s aux articles L. 4138-3 et L. 4138-3-1 , dans les cas autres que ceux pr\u00e9vus \u00e0 l'article L. 4138-12 , lorsque l'affection constat\u00e9e met l'int\u00e9ress\u00e9 dans l'impossibilit\u00e9 d'exercer ses fonctions et qu'elle pr\u00e9sente un caract\u00e8re invalidant et de gravit\u00e9 confirm\u00e9e. Lorsque l'affection survient du fait ou \u00e0 l'occasion de l'exercice des fonctions ou \u00e0 la suite de l'une des causes exceptionnelles pr\u00e9vues \u00e0 l'article L. 27 du code des pensions civiles et militaires de retraite, ce cong\u00e9 est d'une dur\u00e9e maximale de trois ans. Le militaire conserve, dans les conditions d\u00e9finies par d\u00e9cret en Conseil d'Etat, sa r\u00e9mun\u00e9ration. Dans les autres cas, le militaire de carri\u00e8re, ou le militaire servant en vertu d'un contrat r\u00e9unissant au moins trois ans de services militaires, b\u00e9n\u00e9ficie de ce cong\u00e9 pendant une dur\u00e9e maximale de trois ans. L'int\u00e9ress\u00e9 per\u00e7oit, dans les conditions fix\u00e9es par d\u00e9cret en Conseil d'Etat, sa r\u00e9mun\u00e9ration pendant un an, puis une r\u00e9mun\u00e9ration r\u00e9duite de moiti\u00e9 les deux ann\u00e9es qui suivent. Le militaire servant en vertu d'un contrat r\u00e9unissant moins de trois ans de services militaires b\u00e9n\u00e9ficie de ce cong\u00e9, non r\u00e9mun\u00e9r\u00e9, pendant une dur\u00e9e maximale d'un an. Le militaire qui a obtenu un cong\u00e9 de longue maladie ne peut b\u00e9n\u00e9ficier d'un cong\u00e9 de m\u00eame nature, s'il n'a pas auparavant repris l'exercice de ses fonctions pendant un an. Le militaire plac\u00e9 en cong\u00e9 de longue maladie continue \u00e0 figurer sur la liste d'anciennet\u00e9, concourt pour l'avancement \u00e0 l'anciennet\u00e9 et, dans les cas vis\u00e9s au deuxi\u00e8me alin\u00e9a du pr\u00e9sent article, pour l'avancement au choix. Le temps pass\u00e9 en cong\u00e9 est pris en compte pour les droits \u00e0 pension de retraite.",
            "texteHtml": "<p>Le cong\u00e9 de longue maladie est attribu\u00e9, apr\u00e8s \u00e9puisement des droits de cong\u00e9 de maladie ou des droits du cong\u00e9 du bless\u00e9 fix\u00e9s aux <a href='/affichCodeArticle.do?cidTexte=LEGITEXT000006071307&idArticle=LEGIARTI000006540307&dateTexte=&categorieLien=cid'>articles L. 4138-3 et L. 4138-3-1</a>, dans les cas autres que ceux pr\u00e9vus \u00e0 l'article <a href='/affichCodeArticle.do?cidTexte=LEGITEXT000006071307&idArticle=LEGIARTI000029227681&dateTexte=&categorieLien=id' title='Code de la d\u00e9fense. - art. L4138-12 (M)'>L. 4138-12</a>, lorsque l'affection constat\u00e9e met l'int\u00e9ress\u00e9 dans l'impossibilit\u00e9 d'exercer ses fonctions et qu'elle pr\u00e9sente un caract\u00e8re invalidant et de gravit\u00e9 confirm\u00e9e. </p><p>Lorsque l'affection survient du fait ou \u00e0 l'occasion de l'exercice des fonctions ou \u00e0 la suite de l'une des causes exceptionnelles pr\u00e9vues \u00e0 l'article <a href='/affichCodeArticle.do?cidTexte=LEGITEXT000006070302&idArticle=LEGIARTI000006362741&dateTexte=&categorieLien=cid'>L. 27 </a>du code des pensions civiles et militaires de retraite, ce cong\u00e9 est d'une dur\u00e9e maximale de trois ans. Le militaire conserve, dans les conditions d\u00e9finies par d\u00e9cret en Conseil d'Etat, sa r\u00e9mun\u00e9ration. </p><p>Dans les autres cas, le militaire de carri\u00e8re, ou le militaire servant en vertu d'un contrat r\u00e9unissant au moins trois ans de services militaires, b\u00e9n\u00e9ficie de ce cong\u00e9 pendant une dur\u00e9e maximale de trois ans. L'int\u00e9ress\u00e9 per\u00e7oit, dans les conditions fix\u00e9es par d\u00e9cret en Conseil d'Etat, sa r\u00e9mun\u00e9ration pendant un an, puis une r\u00e9mun\u00e9ration r\u00e9duite de moiti\u00e9 les deux ann\u00e9es qui suivent. Le militaire servant en vertu d'un contrat r\u00e9unissant moins de trois ans de services militaires b\u00e9n\u00e9ficie de ce cong\u00e9, non r\u00e9mun\u00e9r\u00e9, pendant une dur\u00e9e maximale d'un an. </p><p>Le militaire qui a obtenu un cong\u00e9 de longue maladie ne peut b\u00e9n\u00e9ficier d'un cong\u00e9 de m\u00eame nature, s'il n'a pas auparavant repris l'exercice de ses fonctions pendant un an. </p><p>Le militaire plac\u00e9 en cong\u00e9 de longue maladie continue \u00e0 figurer sur la liste d'anciennet\u00e9, concourt pour l'avancement \u00e0 l'anciennet\u00e9 et, dans les cas vis\u00e9s au deuxi\u00e8me alin\u00e9a du pr\u00e9sent article, pour l'avancement au choix. Le temps pass\u00e9 en cong\u00e9 est pris en compte pour les droits \u00e0 pension de retraite.</p>",
            "num": "L4138-13",
            "origine": "LEGI",
            "nature": "Article",
            "versionArticle": "3.0",
            "etat": "MODIFIE",
            "dateDebut": 1405123200000,
            "dateFin": 1469145600000,
            "dateDebutExtension": 32472144000000,
            "dateFinExtension": 32472144000000,
            "inap": null,
            "ordre": 128847,
            "context": {
                "titresTM": [
                    {
                        "debut": "2004-12-21",
                        "fin": "2999-01-01",
                        "titre": "Partie l\u00e9gislative",
                        "xPath": "/ARTICLE/CONTEXTE/TEXTE/TM/TITRE_TM",
                        "cid": "LEGISCTA000006096399",
                        "id": "LEGISCTA000006096399",
                        "etat": "VIGUEUR"
                    },
                    {
                        "debut": "2007-03-30",
                        "fin": "2999-01-01",
                        "titre": "PARTIE 4 : LE PERSONNEL MILITAIRE",
                        "xPath": "/ARTICLE/CONTEXTE/TEXTE/TM/TM/TITRE_TM",
                        "cid": "LEGISCTA000006120662",
                        "id": "LEGISCTA000006120662",
                        "etat": "VIGUEUR"
                    },
                    {
                        "debut": "2007-03-30",
                        "fin": "2999-01-01",
                        "titre": "LIVRE Ier : STATUT G\u00c9N\u00c9RAL DES MILITAIRES",
                        "xPath": "/ARTICLE/CONTEXTE/TEXTE/TM/TM/TM/TITRE_TM",
                        "cid": "LEGISCTA000006137720",
                        "id": "LEGISCTA000006137720",
                        "etat": "VIGUEUR"
                    },
                    {
                        "debut": "2007-03-30",
                        "fin": "2999-01-01",
                        "titre": "TITRE III : DISPOSITIONS STATUTAIRES RELATIVES AUX D\u00c9ROULEMENTS DES CARRI\u00c8RES",
                        "xPath": "/ARTICLE/CONTEXTE/TEXTE/TM/TM/TM/TM/TITRE_TM",
                        "cid": "LEGISCTA000006151518",
                        "id": "LEGISCTA000006151518",
                        "etat": "VIGUEUR"
                    },
                    {
                        "debut": "2007-03-30",
                        "fin": "2999-01-01",
                        "titre": "Chapitre VIII : Positions statutaires",
                        "xPath": "/ARTICLE/CONTEXTE/TEXTE/TM/TM/TM/TM/TM/TITRE_TM",
                        "cid": "LEGISCTA000006166980",
                        "id": "LEGISCTA000006166980",
                        "etat": "VIGUEUR"
                    },
                    {
                        "debut": "2007-03-30",
                        "fin": "2999-01-01",
                        "titre": "Section 4 : Non-activit\u00e9",
                        "xPath": "/ARTICLE/CONTEXTE/TEXTE/TM/TM/TM/TM/TM/TM/TITRE_TM",
                        "cid": "LEGISCTA000006182633",
                        "id": "LEGISCTA000006182633",
                        "etat": "VIGUEUR"
                    }
                ],
                "nombreVersionParent": 1,
                "longeurChemin": 50,
                "titreTxt": [
                    {
                        "debut": "2004-12-21",
                        "fin": "2999-01-01",
                        "titre": "Code de la d\u00e9fense",
                        "xPath": "/ARTICLE/CONTEXTE/TEXTE/TITRE_TXT",
                        "cid": "LEGITEXT000006071307",
                        "id": "LEGITEXT000006071307",
                        "etat": "VIGUEUR"
                    }
                ]
            },
            "cid": "LEGIARTI000006540318",
            "cidTexte": null,
            "sectionParentCid": "LEGISCTA000006182633",
            "sectionParentId": "LEGISCTA000006182633",
            "sectionParentTitre": "Section 4 : Non-activit\u00e9",
            "fullSectionsTitre": "Partie l\u00e9gislative &gt; PARTIE 4 : LE PERSONNEL MILITAIRE &gt; LIVRE Ier : STATUT G\u00c9N\u00c9RAL DES MILITAIRES &gt; TITRE III : DISPOSITIONS STATUTAIRES RELATIVES AUX D\u00c9ROULEMENTS DES CARRI\u00c8RES &gt; Chapitre VIII : Positions statutaires &gt; Section 4 : Non-activit\u00e9",
            "refInjection": "IG-20230926",
            "idTechInjection": "LEGIARTI000029227676",
            "idEli": null,
            "idEliAlias": null,
            "calipsos": [],
            "textTitles": [
                {
                    "id": "LEGITEXT000006071307",
                    "titre": "Code de la d\u00e9fense.",
                    "titreLong": "Code de la d\u00e9fense",
                    "etat": "VIGUEUR",
                    "dateDebut": 1103587200000,
                    "dateFin": 32472144000000,
                    "cid": "LEGITEXT000006071307",
                    "datePubli": 32472144000000,
                    "datePubliComputed": null,
                    "dateTexte": 32472144000000,
                    "dateTexteComputed": null,
                    "nature": "CODE",
                    "nor": "",
                    "num": "",
                    "numParution": "",
                    "originePubli": "",
                    "appliGeo": null,
                    "codesNomenclatures": [],
                    "visas": null,
                    "nota": null,
                    "notice": null,
                    "travauxPreparatoires": null,
                    "signataires": null,
                    "dossiersLegislatifs": [],
                    "ancienId": null,
                    "appellations": null
                }
            ],
            "nota": "",
            "notaHtml": "",
            "activitePro": [],
            "numeroBrochure": [],
            "numeroBo": null,
            "conteneurs": [],
            "lienModifications": [
                {
                    "textCid": "JORFTEXT000000466960",
                    "textTitle": "Ordonnance n\u00b0 2007-465 du 29 mars 2007 - art. Annexe (V)",
                    "linkType": "CODIFICATION",
                    "linkOrientation": "source",
                    "articleNum": "Annexe",
                    "articleId": "LEGIARTI000036687012",
                    "natureText": "ORDONNANCE",
                    "datePubliTexte": "2007-03-30",
                    "dateSignaTexte": "2007-03-29",
                    "dateDebutCible": "2007-03-30"
                },
                {
                    "textCid": "JORFTEXT000029218284",
                    "textTitle": "ORDONNANCE n\u00b02014-792 du 10 juillet 2014 - art. 21",
                    "linkType": "MODIFIE",
                    "linkOrientation": "cible",
                    "articleNum": "21",
                    "articleId": "LEGIARTI000029220199",
                    "natureText": "ORDONNANCE",
                    "datePubliTexte": "2014-07-11",
                    "dateSignaTexte": "2014-07-10",
                    "dateDebutCible": "2014-07-12"
                }
            ],
            "lienCitations": [
                {
                    "textCid": "JORFTEXT000042238259",
                    "textTitle": "D\u00e9cret n\u00b02020-1057 du 14 ao\u00fbt 2020 - art. 4 (V)",
                    "linkType": "CITATION",
                    "linkOrientation": "cible",
                    "articleNum": "4",
                    "articleId": "LEGIARTI000042239454",
                    "natureText": "DECRET",
                    "parentCid": null,
                    "numTexte": "2020-1057",
                    "datePubli": 1597449600000,
                    "dateDebut": 1597536000000
                },
                {
                    "textCid": "JORFTEXT000044591334",
                    "textTitle": "Arr\u00eat\u00e9 du 21 d\u00e9cembre 2021 - art. 2, v. init.",
                    "linkType": "CITATION",
                    "linkOrientation": "cible",
                    "articleNum": "2",
                    "articleId": "JORFARTI000044591338",
                    "natureText": "ARRETE",
                    "parentCid": null,
                    "numTexte": "",
                    "datePubli": 1640736000000,
                    "dateDebut": 32472144000000
                },
                {
                    "textCid": "LEGITEXT000006070302",
                    "textTitle": "Code des pensions civiles et militaires de retraite - art. L27",
                    "linkType": "CITATION",
                    "linkOrientation": "source",
                    "articleNum": "L27",
                    "articleId": "LEGIARTI000006362741",
                    "natureText": "CODE",
                    "parentCid": null,
                    "numTexte": "",
                    "datePubli": 32472144000000,
                    "dateDebut": 1565222400000
                },
                {
                    "textCid": "LEGITEXT000006071307",
                    "textTitle": "Code de la d\u00e9fense. - art. L4138-12 (M)",
                    "linkType": "CITATION",
                    "linkOrientation": "source",
                    "articleNum": "L4138-12",
                    "articleId": "LEGIARTI000029227681",
                    "natureText": "CODE",
                    "parentCid": null,
                    "numTexte": "",
                    "datePubli": 32472144000000,
                    "dateDebut": 1405123200000
                },
                {
                    "textCid": "LEGITEXT000006071307",
                    "textTitle": "Code de la d\u00e9fense. - art. L4138-3",
                    "linkType": "CITATION",
                    "linkOrientation": "source",
                    "articleNum": "L4138-3",
                    "articleId": "LEGIARTI000006540307",
                    "natureText": "CODE",
                    "parentCid": null,
                    "numTexte": "",
                    "datePubli": 32472144000000,
                    "dateDebut": 1175212800000
                },
                {
                    "textCid": "LEGITEXT000006071307",
                    "textTitle": "Code de la d\u00e9fense. - art. L4341-1 (VT)",
                    "linkType": "CITATION",
                    "linkOrientation": "cible",
                    "articleNum": "L4341-1",
                    "articleId": "LEGIARTI000037805833",
                    "natureText": "CODE",
                    "parentCid": null,
                    "numTexte": "",
                    "datePubli": 32472144000000,
                    "dateDebut": 1544745600000
                },
                {
                    "textCid": "LEGITEXT000006071307",
                    "textTitle": "Code de la d\u00e9fense. - art. R4138-58 (V)",
                    "linkType": "CITATION",
                    "linkOrientation": "cible",
                    "articleNum": "R4138-58",
                    "articleId": "LEGIARTI000033992875",
                    "natureText": "CODE",
                    "parentCid": null,
                    "numTexte": "",
                    "datePubli": 32472144000000,
                    "dateDebut": 1486339200000
                }
            ],
            "lienConcordes": [
                {
                    "textCid": "JORFTEXT000000808186",
                    "textTitle": "Loi 2005-270 2005-03-24 art. 56",
                    "linkType": "CONCORDANCE",
                    "linkOrientation": "source",
                    "articleNum": "",
                    "articleId": "JORFTEXT000000808186",
                    "natureText": "LOI"
                },
                {
                    "textCid": "JORFTEXT000000808186",
                    "textTitle": "Loi n\u00b02005-270 du 24 mars 2005 - art. 56 (Ab)",
                    "linkType": "CONCORDE",
                    "linkOrientation": "cible",
                    "articleNum": "56",
                    "articleId": "LEGIARTI000006405057",
                    "natureText": "LOI"
                }
            ],
            "lienAutres": [],
            "articleVersions": [
                {
                    "id": "LEGIARTI000006540318",
                    "etat": "MODIFIE",
                    "version": "1.0",
                    "dateDebut": 1175212800000,
                    "dateFin": 1211932800000,
                    "numero": null,
                    "ordre": null
                },
                {
                    "id": "LEGIARTI000018882454",
                    "etat": "MODIFIE",
                    "version": "2.0",
                    "dateDebut": 1211932800000,
                    "dateFin": 1405123200000,
                    "numero": null,
                    "ordre": null
                },
                {
                    "id": "LEGIARTI000029227676",
                    "etat": "MODIFIE",
                    "version": "3.0",
                    "dateDebut": 1405123200000,
                    "dateFin": 1469145600000,
                    "numero": null,
                    "ordre": null
                },
                {
                    "id": "LEGIARTI000033062981",
                    "etat": "MODIFIE",
                    "version": "4.0",
                    "dateDebut": 1469145600000,
                    "dateFin": 1606435200000,
                    "numero": null,
                    "ordre": null
                },
                {
                    "id": "LEGIARTI000042567464",
                    "etat": "VIGUEUR",
                    "version": "5.0",
                    "dateDebut": 1606435200000,
                    "dateFin": 32472144000000,
                    "numero": null,
                    "ordre": null
                }
            ],
            "computedNums": [
                "L4138-13",
                "4138-13"
            ],
            "versionPrecedente": "LEGIARTI000018882454",
            "conditionDiffere": null,
            "historique": null,
            "surtitre": null,
            "renvoi": null,
            "infosComplementaires": null,
            "infosComplementairesHtml": null,
            "infosRestructurationBranche": null,
            "infosRestructurationBrancheHtml": null
        },
        {
            "id": "LEGIARTI000018882454",
            "idTexte": null,
            "type": "AUTONOME",
            "texte": "Le cong\u00e9 de longue maladie est attribu\u00e9, apr\u00e8s \u00e9puisement des droits de cong\u00e9 de maladie fix\u00e9s \u00e0 l'article L.4138-3 , dans les cas autres que ceux pr\u00e9vus \u00e0 l'article L.4138-12 , lorsque l'affection constat\u00e9e met l'int\u00e9ress\u00e9 dans l'impossibilit\u00e9 d'exercer ses fonctions et qu'elle pr\u00e9sente un caract\u00e8re invalidant et de gravit\u00e9 confirm\u00e9e. Lorsque l'affection survient du fait ou \u00e0 l'occasion de l'exercice des fonctions ou \u00e0 la suite de l'une des causes exceptionnelles pr\u00e9vues \u00e0 l'article L.27 du code des pensions civiles et militaires de retraite, ce cong\u00e9 est d'une dur\u00e9e maximale de trois ans. Le militaire conserve, dans les conditions d\u00e9finies par d\u00e9cret en Conseil d'Etat, sa r\u00e9mun\u00e9ration. Dans les autres cas, le militaire de carri\u00e8re, ou le militaire servant en vertu d'un contrat r\u00e9unissant au moins trois ans de services militaires, b\u00e9n\u00e9ficie de ce cong\u00e9 pendant une dur\u00e9e maximale de trois ans. L'int\u00e9ress\u00e9 per\u00e7oit, dans les conditions fix\u00e9es par d\u00e9cret en Conseil d'Etat, sa r\u00e9mun\u00e9ration pendant un an, puis une r\u00e9mun\u00e9ration r\u00e9duite de moiti\u00e9 les deux ann\u00e9es qui suivent. Le militaire servant en vertu d'un contrat r\u00e9unissant moins de trois ans de services militaires b\u00e9n\u00e9ficie de ce cong\u00e9, non r\u00e9mun\u00e9r\u00e9, pendant une dur\u00e9e maximale d'un an. Le militaire qui a obtenu un cong\u00e9 de longue maladie ne peut b\u00e9n\u00e9ficier d'un cong\u00e9 de m\u00eame nature, s'il n'a pas auparavant repris l'exercice de ses fonctions pendant un an. Le militaire plac\u00e9 en cong\u00e9 de longue maladie continue \u00e0 figurer sur la liste d'anciennet\u00e9, concourt pour l'avancement \u00e0 l'anciennet\u00e9 et, dans les cas vis\u00e9s au deuxi\u00e8me alin\u00e9a du pr\u00e9sent article, pour l'avancement au choix. Le temps pass\u00e9 en cong\u00e9 est pris en compte pour les droits \u00e0 pension de retraite.",
            "texteHtml": "<p>Le cong\u00e9 de longue maladie est attribu\u00e9, apr\u00e8s \u00e9puisement des droits de cong\u00e9 de maladie fix\u00e9s \u00e0 l'article <a href='/affichCodeArticle.do?cidTexte=LEGITEXT000006071307&idArticle=LEGIARTI000006540307&dateTexte=&categorieLien=cid'>L.4138-3</a>, dans les cas autres que ceux pr\u00e9vus \u00e0 l'article <a href='/affichCodeArticle.do?cidTexte=LEGITEXT000006071307&idArticle=LEGIARTI000006540317&dateTexte=&categorieLien=cid'>L.4138-12</a>, lorsque l'affection constat\u00e9e met l'int\u00e9ress\u00e9 dans l'impossibilit\u00e9 d'exercer ses fonctions et qu'elle pr\u00e9sente un caract\u00e8re invalidant et de gravit\u00e9 confirm\u00e9e. </p><p>Lorsque l'affection survient du fait ou \u00e0 l'occasion de l'exercice des fonctions ou \u00e0 la suite de l'une des causes exceptionnelles pr\u00e9vues \u00e0 l'article <a href='/affichCodeArticle.do?cidTexte=LEGITEXT000006070302&idArticle=LEGIARTI000006362741&dateTexte=&categorieLien=cid'>L.27</a> du code des pensions civiles et militaires de retraite, ce cong\u00e9 est d'une dur\u00e9e maximale de trois ans. Le militaire conserve, dans les conditions d\u00e9finies par d\u00e9cret en Conseil d'Etat, sa r\u00e9mun\u00e9ration. </p><p>Dans les autres cas, le militaire de carri\u00e8re, ou le militaire servant en vertu d'un contrat r\u00e9unissant au moins trois ans de services militaires, b\u00e9n\u00e9ficie de ce cong\u00e9 pendant une dur\u00e9e maximale de trois ans. L'int\u00e9ress\u00e9 per\u00e7oit, dans les conditions fix\u00e9es par d\u00e9cret en Conseil d'Etat, sa r\u00e9mun\u00e9ration pendant un an, puis une r\u00e9mun\u00e9ration r\u00e9duite de moiti\u00e9 les deux ann\u00e9es qui suivent. Le militaire servant en vertu d'un contrat r\u00e9unissant moins de trois ans de services militaires b\u00e9n\u00e9ficie de ce cong\u00e9, non r\u00e9mun\u00e9r\u00e9, pendant une dur\u00e9e maximale d'un an. </p><p>Le militaire qui a obtenu un cong\u00e9 de longue maladie ne peut b\u00e9n\u00e9ficier d'un cong\u00e9 de m\u00eame nature, s'il n'a pas auparavant repris l'exercice de ses fonctions pendant un an. </p><p>Le militaire plac\u00e9 en cong\u00e9 de longue maladie continue \u00e0 figurer sur la liste d'anciennet\u00e9, concourt pour l'avancement \u00e0 l'anciennet\u00e9 et, dans les cas vis\u00e9s au deuxi\u00e8me alin\u00e9a du pr\u00e9sent article, pour l'avancement au choix. Le temps pass\u00e9 en cong\u00e9 est pris en compte pour les droits \u00e0 pension de retraite.</p>",
            "num": "L4138-13",
            "origine": "LEGI",
            "nature": "Article",
            "versionArticle": "2.0",
            "etat": "MODIFIE",
            "dateDebut": 1211932800000,
            "dateFin": 1405123200000,
            "dateDebutExtension": 32472144000000,
            "dateFinExtension": 32472144000000,
            "inap": null,
            "ordre": 128847,
            "context": {
                "titresTM": [
                    {
                        "debut": "2004-12-21",
                        "fin": "2999-01-01",
                        "titre": "Partie l\u00e9gislative",
                        "xPath": "/ARTICLE/CONTEXTE/TEXTE/TM/TITRE_TM",
                        "cid": "LEGISCTA000006096399",
                        "id": "LEGISCTA000006096399",
                        "etat": "VIGUEUR"
                    },
                    {
                        "debut": "2007-03-30",
                        "fin": "2999-01-01",
                        "titre": "PARTIE 4 : LE PERSONNEL MILITAIRE",
                        "xPath": "/ARTICLE/CONTEXTE/TEXTE/TM/TM/TITRE_TM",
                        "cid": "LEGISCTA000006120662",
                        "id": "LEGISCTA000006120662",
                        "etat": "VIGUEUR"
                    },
                    {
                        "debut": "2007-03-30",
                        "fin": "2999-01-01",
                        "titre": "LIVRE Ier : STATUT G\u00c9N\u00c9RAL DES MILITAIRES",
                        "xPath": "/ARTICLE/CONTEXTE/TEXTE/TM/TM/TM/TITRE_TM",
                        "cid": "LEGISCTA000006137720",
                        "id": "LEGISCTA000006137720",
                        "etat": "VIGUEUR"
                    },
                    {
                        "debut": "2007-03-30",
                        "fin": "2999-01-01",
                        "titre": "TITRE III : DISPOSITIONS STATUTAIRES RELATIVES AUX D\u00c9ROULEMENTS DES CARRI\u00c8RES",
                        "xPath": "/ARTICLE/CONTEXTE/TEXTE/TM/TM/TM/TM/TITRE_TM",
                        "cid": "LEGISCTA000006151518",
                        "id": "LEGISCTA000006151518",
                        "etat": "VIGUEUR"
                    },
                    {
                        "debut": "2007-03-30",
                        "fin": "2999-01-01",
                        "titre": "Chapitre VIII : Positions statutaires",
                        "xPath": "/ARTICLE/CONTEXTE/TEXTE/TM/TM/TM/TM/TM/TITRE_TM",
                        "cid": "LEGISCTA000006166980",
                        "id": "LEGISCTA000006166980",
                        "etat": "VIGUEUR"
                    },
                    {
                        "debut": "2007-03-30",
                        "fin": "2999-01-01",
                        "titre": "Section 4 : Non-activit\u00e9",
                        "xPath": "/ARTICLE/CONTEXTE/TEXTE/TM/TM/TM/TM/TM/TM/TITRE_TM",
                        "cid": "LEGISCTA000006182633",
                        "id": "LEGISCTA000006182633",
                        "etat": "VIGUEUR"
                    }
                ],
                "nombreVersionParent": 1,
                "longeurChemin": 50,
                "titreTxt": [
                    {
                        "debut": "2004-12-21",
                        "fin": "2999-01-01",
                        "titre": "Code de la d\u00e9fense",
                        "xPath": "/ARTICLE/CONTEXTE/TEXTE/TITRE_TXT",
                        "cid": "LEGITEXT000006071307",
                        "id": "LEGITEXT000006071307",
                        "etat": "VIGUEUR"
                    }
                ]
            },
            "cid": "LEGIARTI000006540318",
            "cidTexte": null,
            "sectionParentCid": "LEGISCTA000006182633",
            "sectionParentId": "LEGISCTA000006182633",
            "sectionParentTitre": "Section 4 : Non-activit\u00e9",
            "fullSectionsTitre": "Partie l\u00e9gislative &gt; PARTIE 4 : LE PERSONNEL MILITAIRE &gt; LIVRE Ier : STATUT G\u00c9N\u00c9RAL DES MILITAIRES &gt; TITRE III : DISPOSITIONS STATUTAIRES RELATIVES AUX D\u00c9ROULEMENTS DES CARRI\u00c8RES &gt; Chapitre VIII : Positions statutaires &gt; Section 4 : Non-activit\u00e9",
            "refInjection": "IG-20230926",
            "idTechInjection": "LEGIARTI000018882454",
            "idEli": null,
            "idEliAlias": null,
            "calipsos": [],
            "textTitles": [
                {
                    "id": "LEGITEXT000006071307",
                    "titre": "Code de la d\u00e9fense.",
                    "titreLong": "Code de la d\u00e9fense",
                    "etat": "VIGUEUR",
                    "dateDebut": 1103587200000,
                    "dateFin": 32472144000000,
                    "cid": "LEGITEXT000006071307",
                    "datePubli": 32472144000000,
                    "datePubliComputed": null,
                    "dateTexte": 32472144000000,
                    "dateTexteComputed": null,
                    "nature": "CODE",
                    "nor": "",
                    "num": "",
                    "numParution": "",
                    "originePubli": "",
                    "appliGeo": null,
                    "codesNomenclatures": [],
                    "visas": null,
                    "nota": null,
                    "notice": null,
                    "travauxPreparatoires": null,
                    "signataires": null,
                    "dossiersLegislatifs": [],
                    "ancienId": null,
                    "appellations": null
                }
            ],
            "nota": "",
            "notaHtml": "",
            "activitePro": [],
            "numeroBrochure": [],
            "numeroBo": null,
            "conteneurs": [],
            "lienModifications": [
                {
                    "textCid": "JORFTEXT000000466960",
                    "textTitle": "Ordonnance n\u00b0 2007-465 du 29 mars 2007 - art. Annexe (V)",
                    "linkType": "CODIFICATION",
                    "linkOrientation": "source",
                    "articleNum": "Annexe",
                    "articleId": "LEGIARTI000036687012",
                    "natureText": "ORDONNANCE",
                    "datePubliTexte": "2007-03-30",
                    "dateSignaTexte": "2007-03-29",
                    "dateDebutCible": "2007-03-30"
                },
                {
                    "textCid": "JORFTEXT000018871685",
                    "textTitle": "LOI n\u00b02008-493\n du 26 mai 2008 - art. 3",
                    "linkType": "MODIFIE",
                    "linkOrientation": "cible",
                    "articleNum": "3",
                    "articleId": "LEGIARTI000018875721",
                    "natureText": "LOI",
                    "datePubliTexte": "2008-05-27",
                    "dateSignaTexte": "2008-05-26",
                    "dateDebutCible": "2008-05-28"
                }
            ],
            "lienCitations": [
                {
                    "textCid": "JORFTEXT000042238259",
                    "textTitle": "D\u00e9cret n\u00b02020-1057 du 14 ao\u00fbt 2020 - art. 4 (V)",
                    "linkType": "CITATION",
                    "linkOrientation": "cible",
                    "articleNum": "4",
                    "articleId": "LEGIARTI000042239454",
                    "natureText": "DECRET",
                    "parentCid": null,
                    "numTexte": "2020-1057",
                    "datePubli": 1597449600000,
                    "dateDebut": 1597536000000
                },
                {
                    "textCid": "JORFTEXT000044591334",
                    "textTitle": "Arr\u00eat\u00e9 du 21 d\u00e9cembre 2021 - art. 2, v. init.",
                    "linkType": "CITATION",
                    "linkOrientation": "cible",
                    "articleNum": "2",
                    "articleId": "JORFARTI000044591338",
                    "natureText": "ARRETE",
                    "parentCid": null,
                    "numTexte": "",
                    "datePubli": 1640736000000,
                    "dateDebut": 32472144000000
                },
                {
                    "textCid": "LEGITEXT000006070302",
                    "textTitle": "Code des pensions civiles et militaires de retraite - art. L27",
                    "linkType": "CITATION",
                    "linkOrientation": "source",
                    "articleNum": "L27",
                    "articleId": "LEGIARTI000006362741",
                    "natureText": "CODE",
                    "parentCid": null,
                    "numTexte": "",
                    "datePubli": 32472144000000,
                    "dateDebut": 1565222400000
                },
                {
                    "textCid": "LEGITEXT000006071307",
                    "textTitle": "Code de la d\u00e9fense. - art. L4138-12",
                    "linkType": "CITATION",
                    "linkOrientation": "source",
                    "articleNum": "L4138-12",
                    "articleId": "LEGIARTI000006540317",
                    "natureText": "CODE",
                    "parentCid": null,
                    "numTexte": "",
                    "datePubli": 32472144000000,
                    "dateDebut": 1469145600000
                },
                {
                    "textCid": "LEGITEXT000006071307",
                    "textTitle": "Code de la d\u00e9fense. - art. L4138-3",
                    "linkType": "CITATION",
                    "linkOrientation": "source",
                    "articleNum": "L4138-3",
                    "articleId": "LEGIARTI000006540307",
                    "natureText": "CODE",
                    "parentCid": null,
                    "numTexte": "",
                    "datePubli": 32472144000000,
                    "dateDebut": 1175212800000
                },
                {
                    "textCid": "LEGITEXT000006071307",
                    "textTitle": "Code de la d\u00e9fense. - art. L4341-1 (VT)",
                    "linkType": "CITATION",
                    "linkOrientation": "cible",
                    "articleNum": "L4341-1",
                    "articleId": "LEGIARTI000037805833",
                    "natureText": "CODE",
                    "parentCid": null,
                    "numTexte": "",
                    "datePubli": 32472144000000,
                    "dateDebut": 1544745600000
                },
                {
                    "textCid": "LEGITEXT000006071307",
                    "textTitle": "Code de la d\u00e9fense. - art. R4138-58 (V)",
                    "linkType": "CITATION",
                    "linkOrientation": "cible",
                    "articleNum": "R4138-58",
                    "articleId": "LEGIARTI000033992875",
                    "natureText": "CODE",
                    "parentCid": null,
                    "numTexte": "",
                    "datePubli": 32472144000000,
                    "dateDebut": 1486339200000
                }
            ],
            "lienConcordes": [
                {
                    "textCid": "JORFTEXT000000808186",
                    "textTitle": "Loi 2005-270 2005-03-24 art. 56",
                    "linkType": "CONCORDANCE",
                    "linkOrientation": "source",
                    "articleNum": "",
                    "articleId": "JORFTEXT000000808186",
                    "natureText": "LOI"
                },
                {
                    "textCid": "JORFTEXT000000808186",
                    "textTitle": "Loi n\u00b02005-270 du 24 mars 2005 - art. 56 (Ab)",
                    "linkType": "CONCORDE",
                    "linkOrientation": "cible",
                    "articleNum": "56",
                    "articleId": "LEGIARTI000006405057",
                    "natureText": "LOI"
                }
            ],
            "lienAutres": [],
            "articleVersions": [
                {
                    "id": "LEGIARTI000006540318",
                    "etat": "MODIFIE",
                    "version": "1.0",
                    "dateDebut": 1175212800000,
                    "dateFin": 1211932800000,
                    "numero": null,
                    "ordre": null
                },
                {
                    "id": "LEGIARTI000018882454",
                    "etat": "MODIFIE",
                    "version": "2.0",
                    "dateDebut": 1211932800000,
                    "dateFin": 1405123200000,
                    "numero": null,
                    "ordre": null
                },
                {
                    "id": "LEGIARTI000029227676",
                    "etat": "MODIFIE",
                    "version": "3.0",
                    "dateDebut": 1405123200000,
                    "dateFin": 1469145600000,
                    "numero": null,
                    "ordre": null
                },
                {
                    "id": "LEGIARTI000033062981",
                    "etat": "MODIFIE",
                    "version": "4.0",
                    "dateDebut": 1469145600000,
                    "dateFin": 1606435200000,
                    "numero": null,
                    "ordre": null
                },
                {
                    "id": "LEGIARTI000042567464",
                    "etat": "VIGUEUR",
                    "version": "5.0",
                    "dateDebut": 1606435200000,
                    "dateFin": 32472144000000,
                    "numero": null,
                    "ordre": null
                }
            ],
            "computedNums": [
                "L4138-13",
                "4138-13"
            ],
            "versionPrecedente": "LEGIARTI000006540318",
            "conditionDiffere": null,
            "historique": null,
            "surtitre": null,
            "renvoi": null,
            "infosComplementaires": null,
            "infosComplementairesHtml": null,
            "infosRestructurationBranche": null,
            "infosRestructurationBrancheHtml": null
        },
        {
            "id": "LEGIARTI000006540318",
            "idTexte": null,
            "type": "AUTONOME",
            "texte": "Le cong\u00e9 de longue maladie est attribu\u00e9, apr\u00e8s \u00e9puisement des droits de cong\u00e9 de maladie fix\u00e9s \u00e0 l'article L. 4138-3, dans les cas autres que ceux \u00e9nonc\u00e9s \u00e0 l'article L. 4138-11, lorsque l'affection constat\u00e9e met l'int\u00e9ress\u00e9 dans l'impossibilit\u00e9 d'exercer ses fonctions et qu'elle pr\u00e9sente un caract\u00e8re invalidant et de gravit\u00e9 confirm\u00e9e. Lorsque l'affection survient du fait ou \u00e0 l'occasion de l'exercice des fonctions ou \u00e0 la suite de l'une des causes exceptionnelles pr\u00e9vues \u00e0 l'article L. 27 du code des pensions civiles et militaires de retraite, ce cong\u00e9 est d'une dur\u00e9e maximale de trois ans. Le militaire conserve, dans les conditions d\u00e9finies par d\u00e9cret en Conseil d'Etat, sa r\u00e9mun\u00e9ration. Dans les autres cas, le militaire de carri\u00e8re, ou le militaire servant en vertu d'un contrat r\u00e9unissant au moins trois ans de services militaires, b\u00e9n\u00e9ficie de ce cong\u00e9 pendant une dur\u00e9e maximale de trois ans. L'int\u00e9ress\u00e9 per\u00e7oit, dans les conditions fix\u00e9es par d\u00e9cret en Conseil d'Etat, sa r\u00e9mun\u00e9ration pendant un an, puis une r\u00e9mun\u00e9ration r\u00e9duite de moiti\u00e9 les deux ann\u00e9es qui suivent. Le militaire servant en vertu d'un contrat r\u00e9unissant moins de trois ans de services militaires b\u00e9n\u00e9ficie de ce cong\u00e9, non r\u00e9mun\u00e9r\u00e9, pendant une dur\u00e9e maximale d'un an. Le militaire qui a obtenu un cong\u00e9 de longue maladie ne peut b\u00e9n\u00e9ficier d'un cong\u00e9 de m\u00eame nature, s'il n'a pas auparavant repris l'exercice de ses fonctions pendant un an. Le militaire plac\u00e9 en cong\u00e9 de longue maladie continue \u00e0 figurer sur la liste d'anciennet\u00e9, concourt pour l'avancement \u00e0 l'anciennet\u00e9 et, dans les cas vis\u00e9s au deuxi\u00e8me alin\u00e9a du pr\u00e9sent article, pour l'avancement au choix. Le temps pass\u00e9 en cong\u00e9 est pris en compte pour les droits \u00e0 pension de retraite.",
            "texteHtml": "<p></p>   Le cong\u00e9 de longue maladie est attribu\u00e9, apr\u00e8s \u00e9puisement des droits de cong\u00e9 de maladie fix\u00e9s \u00e0 l'article L. 4138-3, dans les cas autres que ceux \u00e9nonc\u00e9s \u00e0 l'article L. 4138-11, lorsque l'affection constat\u00e9e met l'int\u00e9ress\u00e9 dans l'impossibilit\u00e9 d'exercer ses fonctions et qu'elle pr\u00e9sente un caract\u00e8re invalidant et de gravit\u00e9 confirm\u00e9e.<p></p><p></p>   Lorsque l'affection survient du fait ou \u00e0 l'occasion de l'exercice des fonctions ou \u00e0 la suite de l'une des causes exceptionnelles pr\u00e9vues \u00e0 l'article L. 27 du code des pensions civiles et militaires de retraite, ce cong\u00e9 est d'une dur\u00e9e maximale de trois ans. Le militaire conserve, dans les conditions d\u00e9finies par d\u00e9cret en Conseil d'Etat, sa r\u00e9mun\u00e9ration.<p></p><p></p>   Dans les autres cas, le militaire de carri\u00e8re, ou le militaire servant en vertu d'un contrat r\u00e9unissant au moins trois ans de services militaires, b\u00e9n\u00e9ficie de ce cong\u00e9 pendant une dur\u00e9e maximale de trois ans. L'int\u00e9ress\u00e9 per\u00e7oit, dans les conditions fix\u00e9es par d\u00e9cret en Conseil d'Etat, sa r\u00e9mun\u00e9ration pendant un an, puis une r\u00e9mun\u00e9ration r\u00e9duite de moiti\u00e9 les deux ann\u00e9es qui suivent. Le militaire servant en vertu d'un contrat r\u00e9unissant moins de trois ans de services militaires b\u00e9n\u00e9ficie de ce cong\u00e9, non r\u00e9mun\u00e9r\u00e9, pendant une dur\u00e9e maximale d'un an.<p></p><p></p>   Le militaire qui a obtenu un cong\u00e9 de longue maladie ne peut b\u00e9n\u00e9ficier d'un cong\u00e9 de m\u00eame nature, s'il n'a pas auparavant repris l'exercice de ses fonctions pendant un an.<p></p><p></p>   Le militaire plac\u00e9 en cong\u00e9 de longue maladie continue \u00e0 figurer sur la liste d'anciennet\u00e9, concourt pour l'avancement \u00e0 l'anciennet\u00e9 et, dans les cas vis\u00e9s au deuxi\u00e8me alin\u00e9a du pr\u00e9sent article, pour l'avancement au choix. Le temps pass\u00e9 en cong\u00e9 est pris en compte pour les droits \u00e0 pension de retraite.<p></p>",
            "num": "L4138-13",
            "origine": "LEGI",
            "nature": "Article",
            "versionArticle": "1.0",
            "etat": "MODIFIE",
            "dateDebut": 1175212800000,
            "dateFin": 1211932800000,
            "dateDebutExtension": 32472144000000,
            "dateFinExtension": 32472144000000,
            "inap": null,
            "ordre": 128847,
            "context": {
                "titresTM": [
                    {
                        "debut": "2004-12-21",
                        "fin": "2999-01-01",
                        "titre": "Partie l\u00e9gislative",
                        "xPath": "/ARTICLE/CONTEXTE/TEXTE/TM/TITRE_TM",
                        "cid": "LEGISCTA000006096399",
                        "id": "LEGISCTA000006096399",
                        "etat": "VIGUEUR"
                    },
                    {
                        "debut": "2007-03-30",
                        "fin": "2999-01-01",
                        "titre": "PARTIE 4 : LE PERSONNEL MILITAIRE",
                        "xPath": "/ARTICLE/CONTEXTE/TEXTE/TM/TM/TITRE_TM",
                        "cid": "LEGISCTA000006120662",
                        "id": "LEGISCTA000006120662",
                        "etat": "VIGUEUR"
                    },
                    {
                        "debut": "2007-03-30",
                        "fin": "2999-01-01",
                        "titre": "LIVRE Ier : STATUT G\u00c9N\u00c9RAL DES MILITAIRES",
                        "xPath": "/ARTICLE/CONTEXTE/TEXTE/TM/TM/TM/TITRE_TM",
                        "cid": "LEGISCTA000006137720",
                        "id": "LEGISCTA000006137720",
                        "etat": "VIGUEUR"
                    },
                    {
                        "debut": "2007-03-30",
                        "fin": "2999-01-01",
                        "titre": "TITRE III : DISPOSITIONS STATUTAIRES RELATIVES AUX D\u00c9ROULEMENTS DES CARRI\u00c8RES",
                        "xPath": "/ARTICLE/CONTEXTE/TEXTE/TM/TM/TM/TM/TITRE_TM",
                        "cid": "LEGISCTA000006151518",
                        "id": "LEGISCTA000006151518",
                        "etat": "VIGUEUR"
                    },
                    {
                        "debut": "2007-03-30",
                        "fin": "2999-01-01",
                        "titre": "Chapitre VIII : Positions statutaires",
                        "xPath": "/ARTICLE/CONTEXTE/TEXTE/TM/TM/TM/TM/TM/TITRE_TM",
                        "cid": "LEGISCTA000006166980",
                        "id": "LEGISCTA000006166980",
                        "etat": "VIGUEUR"
                    },
                    {
                        "debut": "2007-03-30",
                        "fin": "2999-01-01",
                        "titre": "Section 4 : Non-activit\u00e9",
                        "xPath": "/ARTICLE/CONTEXTE/TEXTE/TM/TM/TM/TM/TM/TM/TITRE_TM",
                        "cid": "LEGISCTA000006182633",
                        "id": "LEGISCTA000006182633",
                        "etat": "VIGUEUR"
                    }
                ],
                "nombreVersionParent": 1,
                "longeurChemin": 50,
                "titreTxt": [
                    {
                        "debut": "2004-12-21",
                        "fin": "2999-01-01",
                        "titre": "Code de la d\u00e9fense",
                        "xPath": "/ARTICLE/CONTEXTE/TEXTE/TITRE_TXT",
                        "cid": "LEGITEXT000006071307",
                        "id": "LEGITEXT000006071307",
                        "etat": "VIGUEUR"
                    }
                ]
            },
            "cid": "LEGIARTI000006540318",
            "cidTexte": null,
            "sectionParentCid": "LEGISCTA000006182633",
            "sectionParentId": "LEGISCTA000006182633",
            "sectionParentTitre": "Section 4 : Non-activit\u00e9",
            "fullSectionsTitre": "Partie l\u00e9gislative &gt; PARTIE 4 : LE PERSONNEL MILITAIRE &gt; LIVRE Ier : STATUT G\u00c9N\u00c9RAL DES MILITAIRES &gt; TITRE III : DISPOSITIONS STATUTAIRES RELATIVES AUX D\u00c9ROULEMENTS DES CARRI\u00c8RES &gt; Chapitre VIII : Positions statutaires &gt; Section 4 : Non-activit\u00e9",
            "refInjection": "IG-20230926",
            "idTechInjection": "LEGIARTI000006540318",
            "idEli": null,
            "idEliAlias": null,
            "calipsos": [],
            "textTitles": [
                {
                    "id": "LEGITEXT000006071307",
                    "titre": "Code de la d\u00e9fense.",
                    "titreLong": "Code de la d\u00e9fense",
                    "etat": "VIGUEUR",
                    "dateDebut": 1103587200000,
                    "dateFin": 32472144000000,
                    "cid": "LEGITEXT000006071307",
                    "datePubli": 32472144000000,
                    "datePubliComputed": null,
                    "dateTexte": 32472144000000,
                    "dateTexteComputed": null,
                    "nature": "CODE",
                    "nor": "",
                    "num": "",
                    "numParution": "",
                    "originePubli": "",
                    "appliGeo": null,
                    "codesNomenclatures": [],
                    "visas": null,
                    "nota": null,
                    "notice": null,
                    "travauxPreparatoires": null,
                    "signataires": null,
                    "dossiersLegislatifs": [],
                    "ancienId": null,
                    "appellations": null
                }
            ],
            "nota": "",
            "notaHtml": "",
            "activitePro": [],
            "numeroBrochure": [],
            "numeroBo": null,
            "conteneurs": [],
            "lienModifications": [
                {
                    "textCid": "JORFTEXT000000466960",
                    "textTitle": "Ordonnance n\u00b0 2007-465 du 29 mars 2007 - art. Annexe (V)",
                    "linkType": "CODIFICATION",
                    "linkOrientation": "source",
                    "articleNum": "Annexe",
                    "articleId": "LEGIARTI000036687012",
                    "natureText": "ORDONNANCE",
                    "datePubliTexte": "2007-03-30",
                    "dateSignaTexte": "2007-03-29",
                    "dateDebutCible": "2007-03-30"
                }
            ],
            "lienCitations": [
                {
                    "textCid": "JORFTEXT000042238259",
                    "textTitle": "D\u00e9cret n\u00b02020-1057 du 14 ao\u00fbt 2020 - art. 4 (V)",
                    "linkType": "CITATION",
                    "linkOrientation": "cible",
                    "articleNum": "4",
                    "articleId": "LEGIARTI000042239454",
                    "natureText": "DECRET",
                    "parentCid": null,
                    "numTexte": "2020-1057",
                    "datePubli": 1597449600000,
                    "dateDebut": 1597536000000
                },
                {
                    "textCid": "JORFTEXT000044591334",
                    "textTitle": "Arr\u00eat\u00e9 du 21 d\u00e9cembre 2021 - art. 2, v. init.",
                    "linkType": "CITATION",
                    "linkOrientation": "cible",
                    "articleNum": "2",
                    "articleId": "JORFARTI000044591338",
                    "natureText": "ARRETE",
                    "parentCid": null,
                    "numTexte": "",
                    "datePubli": 1640736000000,
                    "dateDebut": 32472144000000
                },
                {
                    "textCid": "LEGITEXT000006071307",
                    "textTitle": "Code de la d\u00e9fense. - art. L4341-1 (VT)",
                    "linkType": "CITATION",
                    "linkOrientation": "cible",
                    "articleNum": "L4341-1",
                    "articleId": "LEGIARTI000037805833",
                    "natureText": "CODE",
                    "parentCid": null,
                    "numTexte": "",
                    "datePubli": 32472144000000,
                    "dateDebut": 1544745600000
                },
                {
                    "textCid": "LEGITEXT000006071307",
                    "textTitle": "Code de la d\u00e9fense. - art. R4138-58 (V)",
                    "linkType": "CITATION",
                    "linkOrientation": "cible",
                    "articleNum": "R4138-58",
                    "articleId": "LEGIARTI000033992875",
                    "natureText": "CODE",
                    "parentCid": null,
                    "numTexte": "",
                    "datePubli": 32472144000000,
                    "dateDebut": 1486339200000
                }
            ],
            "lienConcordes": [
                {
                    "textCid": "JORFTEXT000000808186",
                    "textTitle": "Loi 2005-270 2005-03-24 art. 56",
                    "linkType": "CONCORDANCE",
                    "linkOrientation": "source",
                    "articleNum": "",
                    "articleId": "JORFTEXT000000808186",
                    "natureText": "LOI"
                },
                {
                    "textCid": "JORFTEXT000000808186",
                    "textTitle": "Loi n\u00b02005-270 du 24 mars 2005 - art. 56 (Ab)",
                    "linkType": "CONCORDE",
                    "linkOrientation": "cible",
                    "articleNum": "56",
                    "articleId": "LEGIARTI000006405057",
                    "natureText": "LOI"
                }
            ],
            "lienAutres": [],
            "articleVersions": [
                {
                    "id": "LEGIARTI000006540318",
                    "etat": "MODIFIE",
                    "version": "1.0",
                    "dateDebut": 1175212800000,
                    "dateFin": 1211932800000,
                    "numero": null,
                    "ordre": null
                },
                {
                    "id": "LEGIARTI000018882454",
                    "etat": "MODIFIE",
                    "version": "2.0",
                    "dateDebut": 1211932800000,
                    "dateFin": 1405123200000,
                    "numero": null,
                    "ordre": null
                },
                {
                    "id": "LEGIARTI000029227676",
                    "etat": "MODIFIE",
                    "version": "3.0",
                    "dateDebut": 1405123200000,
                    "dateFin": 1469145600000,
                    "numero": null,
                    "ordre": null
                },
                {
                    "id": "LEGIARTI000033062981",
                    "etat": "MODIFIE",
                    "version": "4.0",
                    "dateDebut": 1469145600000,
                    "dateFin": 1606435200000,
                    "numero": null,
                    "ordre": null
                },
                {
                    "id": "LEGIARTI000042567464",
                    "etat": "VIGUEUR",
                    "version": "5.0",
                    "dateDebut": 1606435200000,
                    "dateFin": 32472144000000,
                    "numero": null,
                    "ordre": null
                }
            ],
            "computedNums": [
                "L4138-13",
                "4138-13"
            ],
            "versionPrecedente": null,
            "conditionDiffere": null,
            "historique": null,
            "surtitre": null,
            "renvoi": null,
            "infosComplementaires": null,
            "infosComplementairesHtml": null,
            "infosRestructurationBranche": null,
            "infosRestructurationBrancheHtml": null
        }
    ]
}